abx_plugin_archivedotorg/__init__.py
abx_plugin_archivedotorg/archive_org.py
abx_plugin_archivedotorg/config.py
abx_plugin_archivedotorg-2024.10.28.dist-info/METADATA
abx_plugin_archivedotorg-2024.10.28.dist-info/WHEEL
abx_plugin_archivedotorg-2024.10.28.dist-info/entry_points.txt
abx_plugin_archivedotorg-2024.10.28.dist-info/RECORD
